arma3cli/__init__.py
arma3cli/cli.py
arma3cli/cmd/__init__.py
arma3cli/cmd/helpmenu.py
arma3cli/data/help.json
arma3cli-0.7.0.dist-info/METADATA
arma3cli-0.7.0.dist-info/WHEEL
arma3cli-0.7.0.dist-info/entry_points.txt
arma3cli-0.7.0.dist-info/RECORD
