Metadata-Version: 2.4
Name: arma3cli
Version: 0.7.0
Summary: CLI tool for deploying and managing Arma 3 servers
Author: Andrew Wade
Requires-Python: >=3.8.1
Requires-Dist: click>=8.1.7
Requires-Dist: rich>=13.7.0
